kubespawner/__init__.py
kubespawner/objects.py
kubespawner/spawner.py
kubespawner/traitlets.py
kubespawner/utils.py
sqrekubespawner/__init__.py
sqrekubespawner/obj2.py
sqrekubespawner/objects.py
sqrekubespawner/spawner.py
sqrekubespawner/traitlets.py
sqrekubespawner/utils.py
sqrekubespawner-0.1.0.dist-info/DESCRIPTION.rst
sqrekubespawner-0.1.0.dist-info/METADATA
sqrekubespawner-0.1.0.dist-info/RECORD
sqrekubespawner-0.1.0.dist-info/WHEEL
sqrekubespawner-0.1.0.dist-info/metadata.json
sqrekubespawner-0.1.0.dist-info/top_level.txt
