Metadata-Version: 2.0
Name: sqrekubespawner
Version: 0.1.0
Summary: LSST SQuaRE flavor of KubeSpawner
Home-page: http://github.com/lsst-sqre/kubespawner
Author: Adam Thornton (based on work by Yuvi Panda)
Author-email: athornton@lsst.org
License: BSD
Platform: UNKNOWN
Requires-Dist: escapism
Requires-Dist: jupyterhub
Requires-Dist: kubernetes (==2.*)
Requires-Dist: pycurl
Requires-Dist: pyyaml
